swarmauri_tool_jupyterclearoutput/JupyterClearOutputTool.py
swarmauri_tool_jupyterclearoutput/__init__.py
swarmauri_tool_jupyterclearoutput-0.7.5.dist-info/LICENSE
swarmauri_tool_jupyterclearoutput-0.7.5.dist-info/METADATA
swarmauri_tool_jupyterclearoutput-0.7.5.dist-info/WHEEL
swarmauri_tool_jupyterclearoutput-0.7.5.dist-info/entry_points.txt
swarmauri_tool_jupyterclearoutput-0.7.5.dist-info/RECORD
