Metadata-Version: 2.3
Name: swarmauri_tool_jupyterclearoutput
Version: 0.7.5
Summary: A tool designed to clear all outputs from a Jupyter Notebook using nbconvert’s ClearOutputPreprocessor, preparing the notebook for sharing or version control.
License: Apache-2.0
Author: Jacob Stewart
Author-email: jacob@swarmauri.com
Requires-Python: >=3.10,<3.13
Classifier: License :: OSI Approved :: Apache Software License
Classifier: Programming Language :: Python :: 3.10
Classifier: Programming Language :: Python :: 3.11
Classifier: Programming Language :: Python :: 3.12
Classifier: Programming Language :: Python :: 3.13
Requires-Dist: nbconvert (>=7.16.6)
Requires-Dist: swarmauri_base
Requires-Dist: swarmauri_core
Requires-Dist: swarmauri_standard
